huaweicloudsdkga/__init__.py
huaweicloudsdkga/v1/__init__.py
huaweicloudsdkga/v1/ga_async_client.py
huaweicloudsdkga/v1/ga_client.py
huaweicloudsdkga/v1/model/__init__.py
huaweicloudsdkga/v1/model/accelerate_ip.py
huaweicloudsdkga/v1/model/accelerator_detail.py
huaweicloudsdkga/v1/model/add_ip_group_ip_request.py
huaweicloudsdkga/v1/model/add_ip_group_ip_request_body.py
huaweicloudsdkga/v1/model/add_ip_group_ip_response.py
huaweicloudsdkga/v1/model/area.py
huaweicloudsdkga/v1/model/associate_listener_request.py
huaweicloudsdkga/v1/model/associate_listener_request_body.py
huaweicloudsdkga/v1/model/associate_listener_response.py
huaweicloudsdkga/v1/model/byoip_pool.py
huaweicloudsdkga/v1/model/client_affinity.py
huaweicloudsdkga/v1/model/config_status.py
huaweicloudsdkga/v1/model/count_resources_by_tag_request.py
huaweicloudsdkga/v1/model/count_resources_by_tag_response.py
huaweicloudsdkga/v1/model/create_accelerator_option.py
huaweicloudsdkga/v1/model/create_accelerator_option_ip_sets.py
huaweicloudsdkga/v1/model/create_accelerator_request.py
huaweicloudsdkga/v1/model/create_accelerator_request_body.py
huaweicloudsdkga/v1/model/create_accelerator_response.py
huaweicloudsdkga/v1/model/create_endpoint_group_option.py
huaweicloudsdkga/v1/model/create_endpoint_group_request.py
huaweicloudsdkga/v1/model/create_endpoint_group_request_body.py
huaweicloudsdkga/v1/model/create_endpoint_group_response.py
huaweicloudsdkga/v1/model/create_endpoint_option.py
huaweicloudsdkga/v1/model/create_endpoint_request.py
huaweicloudsdkga/v1/model/create_endpoint_request_body.py
huaweicloudsdkga/v1/model/create_endpoint_response.py
huaweicloudsdkga/v1/model/create_health_check_option.py
huaweicloudsdkga/v1/model/create_health_check_request.py
huaweicloudsdkga/v1/model/create_health_check_request_body.py
huaweicloudsdkga/v1/model/create_health_check_response.py
huaweicloudsdkga/v1/model/create_ip_group_ip_option.py
huaweicloudsdkga/v1/model/create_ip_group_option.py
huaweicloudsdkga-3.1.184.dist-info/METADATA
huaweicloudsdkga-3.1.184.dist-info/WHEEL
huaweicloudsdkga-3.1.184.dist-info/licenses/LICENSE
huaweicloudsdkga-3.1.184.dist-info/RECORD
